deepsentinel/__init__.py
deepsentinel/client.py
deepsentinel/config.py
deepsentinel/exceptions.py
deepsentinel/interfaces.py
deepsentinel/types.py
deepsentinel/api/__init__.py
deepsentinel/api/audit.py
deepsentinel/api/client.py
deepsentinel/api/compliance.py
deepsentinel/audit/__init__.py
deepsentinel/audit/client.py
deepsentinel/audit/events.py
deepsentinel/cache/__init__.py
deepsentinel/cache/client.py
deepsentinel/compliance/__init__.py
deepsentinel/compliance/engine.py
deepsentinel/compliance/interceptor.py
deepsentinel/compliance/policies.py
deepsentinel/compliance/detection/__init__.py
deepsentinel/compliance/detection/engine.py
deepsentinel/compliance/detection/patterns.py
deepsentinel/compliance/detection/pci.py
deepsentinel/compliance/detection/phi.py
deepsentinel/compliance/detection/pii.py
deepsentinel/mcp/__init__.py
deepsentinel/metrics/__init__.py
deepsentinel/metrics/collector.py
deepsentinel/middleware/__init__.py
deepsentinel/middleware/base.py
deepsentinel/providers/__init__.py
deepsentinel/providers/anthropic.py
deepsentinel/providers/base.py
deepsentinel/providers/openai.py
deepsentinel/providers/registry.py
deepsentinel_sdk-1.0.2.dist-info/METADATA
deepsentinel_sdk-1.0.2.dist-info/WHEEL
deepsentinel_sdk-1.0.2.dist-info/licenses/LICENSE
deepsentinel_sdk-1.0.2.dist-info/RECORD
